README.md
setup.cfg
setup.py
terrapin/__init__.py
terrapin/exceptions.py
terrapin/lexer.py
terrapin/parser.py
terrapin/parsetab.py
terrapin/render_full.py
terrapin/render_simple.py
terrapin/used_variables.py
terrapin.egg-info/PKG-INFO
terrapin.egg-info/SOURCES.txt
terrapin.egg-info/dependency_links.txt
terrapin.egg-info/requires.txt
terrapin.egg-info/top_level.txt