Metadata-Version: 1.0
Name: terrapin
Version: 0.0.19
Summary: A very lightweight template language
Home-page: https://github.com/DistilledLtd/terrapin
Author: Distilled Ltd
Author-email: randd@distilled.net
License: UNKNOWN
Platform: UNKNOWN
